pypher/__init__.py
pypher/addpixscl.py
pypher/fitsutils.py
pypher/parser.py
pypher/pypher.py
pypher/tests/__init__.py
pypher/tests/conftest.py
pypher/tests/test_pypher.py
pypher-0.7.3.dist-info/LICENSE
pypher-0.7.3.dist-info/METADATA
pypher-0.7.3.dist-info/WHEEL
pypher-0.7.3.dist-info/entry_points.txt
pypher-0.7.3.dist-info/top_level.txt
pypher-0.7.3.dist-info/RECORD
