Metadata-Version: 2.1
Name: pypher
Version: 0.7.3
Summary: Python-based PSF Homogenization kERnels production
Home-page: http://pypher.readthedocs.org/en/latest/
Download-URL: https://github.com/aboucaud/pypher
Author: Alexandre Boucaud
Author-email: alexandre.boucaud@apc.in2p3.fr
License: New BSD
Classifier: Programming Language :: Python
Classifier: Development Status :: 4 - Beta
Classifier: License :: OSI Approved :: BSD License
Classifier: Intended Audience :: Science/Research
Classifier: Topic :: Scientific/Engineering :: Astronomy
Classifier: Operating System :: OS Independent
Classifier: Programming Language :: Python :: 2.7
Classifier: Programming Language :: Python :: 3
License-File: LICENSE
Requires-Dist: numpy>=1.7.2
Requires-Dist: scipy>=0.9
Requires-Dist: astropy>=2.0
